[
  {
    "code": "CMIRON500GIFT",
    "rewards": "500 Rune Fragments, 500 Low Tier Mana Crystals, and 1mil Gold",
    "date": "2025-10-01T16:30:03.459Z"
  },
  {
    "code": "FALLUPDAT3",
    "rewards": "1k Essence Stones and Ten First Edition Of Magic Crafting",
    "date": "2025-10-01T16:30:03.459Z"
  },
  {
    "code": "SORRYFORBUG",
    "rewards": "10mil Gold",
    "date": "2025-10-01T16:30:03.459Z"
  },
  {
    "code": "NEWEAPONS",
    "rewards": "Ten Weapon Custom Draw Tickets and 40 Weapon Enhancement Gear Iii",
    "date": "2025-10-01T16:30:03.459Z"
  },
  {
    "code": "DEV_10_N0TE",
    "rewards": "Free In Game Rewards",
    "date": "2025-10-01T16:30:03.459Z"
  },
  {
    "code": "S3PUPDATE:",
    "rewards": "100 Advanced Mana Crystals and 200 Artifact Enhancement Chip Ii",
    "date": "2025-10-01T16:30:03.459Z"
  },
  {
    "code": "FATHERSUNG",
    "rewards": "Free In Game Rewards",
    "date": "2025-10-01T16:30:03.459Z"
  },
  {
    "code": "SUNGFAMILY",
    "rewards": "Free In Game Rewards",
    "date": "2025-10-01T16:30:03.459Z"
  },
  {
    "code": "BEMYIDLE",
    "rewards": "One Mana Power Extract and Ten Shadow Skill Scrolls Ii",
    "date": "2025-09-12T16:00:03.759Z"
  },
  {
    "code": "BOSSBOSSBOSS",
    "rewards": "Ten Custom Draw Tickets",
    "date": "2025-09-12T16:00:03.759Z"
  },
  {
    "code": "DEVNOTEARCHUPD",
    "rewards": "20 Custom Draw Tickets, 1mil Gold, and 1k Low Tier Mana Crystals",
    "date": "2025-09-01T12:30:05.611Z"
  },
  {
    "code": "HAPPY500TH",
    "rewards": "1mil Gold, 1k Rune Fragments, and 500 Blessing Powder",
    "date": "2025-09-01T12:30:05.611Z"
  },
  {
    "code": "SOMINQI",
    "rewards": "1mil Gold and Five Uncommon Skill Run Chests",
    "date": "2025-09-01T12:30:05.611Z"
  },
  {
    "code": "JUICYZAFF",
    "rewards": "100k Gold and 50 Blessing Powder",
    "date": "2025-09-01T12:30:05.611Z"
  },
  {
    "code": "2NDIDLECOLLAB",
    "rewards": "Ten Custom Draw Tickets and 50 Weapon Enhancement Gear Iii",
    "date": "2025-09-01T12:30:05.611Z"
  },
  {
    "code": "AUG28THUD",
    "rewards": "Five Abyssal Crystals, 100 Traces Of Shadow, and 1k Low Tier Mana Crystals",
    "date": "2025-09-01T12:30:05.611Z"
  },
  {
    "code": "PAYNECHULED",
    "rewards": "100k Gold and 50 Blessing Powder",
    "date": "2025-09-01T12:30:05.611Z"
  },
  {
    "code": "BOTKING",
    "rewards": "100k Gold and 100 Rune Fragments",
    "date": "2025-09-01T12:30:05.611Z"
  },
  {
    "code": "HIVEPORDY",
    "rewards": "100k Gold and 100 Rune Fragments",
    "date": "2025-09-01T12:30:05.611Z"
  },
  {
    "code": "IDLEHUNTERTIME",
    "rewards": "Ten Custom Draw Tickets",
    "date": "2025-09-01T12:30:05.611Z"
  },
  {
    "code": "THXSLVARISETHX",
    "rewards": "Free Gold",
    "date": "2025-08-26T18:00:03.949Z"
  },
  {
    "code": "WORLD1STLEVELUP",
    "rewards": "Free Essence Stones",
    "date": "2025-08-26T18:00:03.949Z"
  },
  {
    "code": "STAYSHARP",
    "rewards": "25,000 Gold and a Gate Key",
    "date": "2025-08-26T18:00:03.949Z"
  },
  {
    "code": "WHOSNATIONALL3VEL",
    "rewards": "1000 Essence Stones",
    "date": "2025-08-26T18:00:03.949Z"
  },
  {
    "code": "THANXTOGLOBALHUNTERS",
    "rewards": "500 Essence Stones",
    "date": "2025-08-26T18:00:03.949Z"
  },
  {
    "code": "ENJOYSUMMERR",
    "rewards": "Ten Custom Draw Tickets",
    "date": "2025-08-26T18:00:03.949Z"
  },
  {
    "code": "NLHCSTREAM",
    "rewards": "10 Custom Draw Tickets",
    "date": "2025-08-26T18:00:03.949Z"
  }
]